starccato_sampler/__init__.py
starccato_sampler/_version.py
starccato_sampler/bayes_factor.py
starccato_sampler/optimise_start.py
starccato_sampler/post_proc.py
starccato_sampler/pp_test.py
starccato_sampler/sampler.py
starccato_sampler/utils.py
starccato_sampler/core/__init__.py
starccato_sampler/core/bayesian_functions.py
starccato_sampler/core/mcmc.py
starccato_sampler/core/ns.py
starccato_sampler/evidence/__init__.py
starccato_sampler/evidence/gaussian_approximation_evidence.py
starccato_sampler/evidence/gss_evidence.py
starccato_sampler/evidence/stepping_stone_evidence.py
starccato_sampler/plotting/__init__.py
starccato_sampler/plotting/plot_1d_marginals.py
starccato_sampler/plotting/plot_ci.py
starccato_sampler/plotting/plot_pe_comparison.py
starccato_sampler/plotting/plot_sampler_diagnostics.py
starccato_sampler-0.0.15.dist-info/METADATA
starccato_sampler-0.0.15.dist-info/WHEEL
starccato_sampler-0.0.15.dist-info/top_level.txt
starccato_sampler-0.0.15.dist-info/RECORD
