Metadata-Version: 2.4
Name: starccato_sampler
Version: 0.0.15
Summary: Tools for parameter estimation with JAX-VAE model.
Author-email: Starccato Team <avi.vajpeyi@gmail.com>
Project-URL: Homepage, https://starccato.github.io/starccato_sampler/
Project-URL: Bug Reports, https://giuthub.com/starccato/starccato_sampler/issues
Project-URL: Source, https://github.com/starccato/starccato_sampler/
Classifier: Development Status :: 3 - Alpha
Classifier: Intended Audience :: Science/Research
Classifier: License :: OSI Approved :: MIT License
Classifier: Operating System :: OS Independent
Classifier: Programming Language :: Python :: 3.8
Requires-Python: >=3.9
Requires-Dist: jax
Requires-Dist: flax
Requires-Dist: numpy
Requires-Dist: matplotlib
Requires-Dist: pandas
Requires-Dist: h5py
Requires-Dist: numpyro
Requires-Dist: jaxns
Requires-Dist: jaxtyping
Requires-Dist: arviz
Requires-Dist: corner
Requires-Dist: pillow
Requires-Dist: natsort
Requires-Dist: starccato-jax
Provides-Extra: dev
Requires-Dist: lartillot_gaussian; extra == "dev"
Requires-Dist: pytest; extra == "dev"
Requires-Dist: pytest-cov; extra == "dev"
Requires-Dist: flake8>=5.0.4; extra == "dev"
Requires-Dist: black>=22.12.0; extra == "dev"
Requires-Dist: black[jupyter]>=22.12.0; extra == "dev"
Requires-Dist: isort; extra == "dev"
Requires-Dist: mypy; extra == "dev"
Requires-Dist: jupyter-book; extra == "dev"
Requires-Dist: pre-commit; extra == "dev"
